pastegram/__init__.py
pastegram/classes.py
pastegram/constants.py
pastegram/errors.py
pastegram/functions.py
pastegram/utils.py
pastegram-1.0.1.dist-info/LICENSE
pastegram-1.0.1.dist-info/METADATA
pastegram-1.0.1.dist-info/WHEEL
pastegram-1.0.1.dist-info/top_level.txt
pastegram-1.0.1.dist-info/RECORD
