Metadata-Version: 2.1
Name: pastegram
Version: 1.0.1
Summary: A set of simple functions to upload and fetch pastes on paste.uploadgram.me
Home-page: https://github.com/Uploadgram/paste-py
Author: Pato05
Author-email: pato05mc@gmail.com
License: UNKNOWN
Project-URL: Bug Tracker, https://github.com/Uploadgram/paste-py/issues
Platform: UNKNOWN
Classifier: Programming Language :: Python :: 3
Classifier: License :: OSI Approved :: MIT License
Classifier: Operating System :: OS Independent
Requires-Python: >=3.0
License-File: LICENSE
Requires-Dist: pycryptodomex (==3.10.1)
Requires-Dist: requests (==2.26.0)
